ameilisearch/__init__.py
ameilisearch/_httprequests.py
ameilisearch/client.py
ameilisearch/config.py
ameilisearch/errors.py
ameilisearch/index.py
ameilisearch/py.typed
ameilisearch/task.py
tests/__init__.py
tests/common.py
tests/conftest.py
tests/helper.py
tests/types.py
ameilisearch-0.3.4.dist-info/LICENSE
ameilisearch-0.3.4.dist-info/METADATA
ameilisearch-0.3.4.dist-info/WHEEL
ameilisearch-0.3.4.dist-info/top_level.txt
ameilisearch-0.3.4.dist-info/RECORD
