Metadata-Version: 2.1
Name: ameilisearch
Version: 0.3.4
Summary: The python async client for MeiliSearch API.
Home-page: https://github.com/saidbysolo/ameilisearch
Author: SaidBySolo
Author-email: saidbysolo@gmail.com
License: UNKNOWN
Project-URL: Documentation, https://docs.meilisearch.com/
Keywords: search python meilisearch
Platform: UNKNOWN
Classifier: Programming Language :: Python :: 3.6
Classifier: Programming Language :: Python :: 3.7
Classifier: Programming Language :: Python :: 3.8
Classifier: Programming Language :: Python :: 3.9
Classifier: License :: OSI Approved :: MIT License
Classifier: Operating System :: OS Independent
Requires-Python: >=3
License-File: LICENSE
Requires-Dist: aiohttp
